areaofShapesLib/__init__.py
areaofShapesLib/myFunctions.py
test/__init__.py
test/test_myFunctions.py
AreaOfShapesLib-5.1.dist-info/LICENSE
AreaOfShapesLib-5.1.dist-info/METADATA
AreaOfShapesLib-5.1.dist-info/WHEEL
AreaOfShapesLib-5.1.dist-info/top_level.txt
AreaOfShapesLib-5.1.dist-info/RECORD
