Metadata-Version: 2.1
Name: AreaOfShapesLib
Version: 5.1
Summary: A Python library for performing arithmetic operations related to the area of different shapes
Home-page: https://github.com/mjfctor/ArithmeticOperations
Author: mjfctor
Author-email: emjayfactor@gmail.com
License: MIT
Classifier: Development Status :: 3 - Alpha
Classifier: Intended Audience :: Developers
Classifier: License :: OSI Approved :: MIT License
Classifier: Programming Language :: Python
Classifier: Programming Language :: Python :: 3
Classifier: Programming Language :: Python :: 3.6
Classifier: Programming Language :: Python :: 3.7
Classifier: Programming Language :: Python :: 3.8
Classifier: Programming Language :: Python :: 3.9
Requires-Python: >=3.6
License-File: LICENSE
